nciscraper/__init__.py
nciscraper/core.py
nciscraper/utils.py
nciscraper-0.4.0.dist-info/LICENSE
nciscraper-0.4.0.dist-info/METADATA
nciscraper-0.4.0.dist-info/WHEEL
nciscraper-0.4.0.dist-info/top_level.txt
nciscraper-0.4.0.dist-info/RECORD
