Metadata-Version: 2.1
Name: nciscraper
Version: 0.4.0
Summary: A Python package to fetch web content using different advance methods.
Home-page: https://github.com/Tux-MacG1v/nciscraper
Author: Tux MacGiver
Author-email: tuxmacg1v991@gmail.com
License: MIT
Classifier: Programming Language :: Python :: 3
Classifier: License :: OSI Approved :: MIT License
Classifier: Operating System :: OS Independent
Requires-Python: >=3.6
License-File: LICENSE
Requires-Dist: requests
Requires-Dist: cloudscraper
Requires-Dist: selenium
Requires-Dist: seleniumbase
Requires-Dist: playwright
Requires-Dist: beautifulsoup4
Requires-Dist: fake_useragent
Requires-Dist: webdriver-manager
Requires-Dist: tenacity
